libgraph/__init__.py
libgraph/algorithms.py
libgraph/graphs.py
libgraph/traversals.py
libgraph-0.0.3.dist-info/DESCRIPTION.rst
libgraph-0.0.3.dist-info/METADATA
libgraph-0.0.3.dist-info/metadata.json
libgraph-0.0.3.dist-info/RECORD
libgraph-0.0.3.dist-info/top_level.txt
libgraph-0.0.3.dist-info/WHEEL
tests/__init__.py
tests/runtests.py
tests/test_algos.py
tests/test_bfs.py
tests/test_dfs.py
tests/test_graph.py
tests/libgraph/__init__.py
tests/libgraph/algorithms.py
tests/libgraph/graphs.py
tests/libgraph/traversals.py
